{
  "links" : {
    "next" : "https://api.nasa.gov/neo/rest/v1/feed?start_date=2016-01-23&end_date=2016-01-23&detailed=true&api_key=t0TVs3DtDT2H8Oy2Zy8m2eVrNsAVKAexjcZXUckd",
    "prev" : "https://api.nasa.gov/neo/rest/v1/feed?start_date=2016-01-21&end_date=2016-01-21&detailed=true&api_key=t0TVs3DtDT2H8Oy2Zy8m2eVrNsAVKAexjcZXUckd",
    "self" : "https://api.nasa.gov/neo/rest/v1/feed?start_date=2016-01-22&end_date=2016-01-22&detailed=true&api_key=t0TVs3DtDT2H8Oy2Zy8m2eVrNsAVKAexjcZXUckd"
  },
  "element_count" : 12,
  "near_earth_objects" : {
    "2016-01-22" : [ {
      "links" : {
        "self" : "https://api.nasa.gov/neo/rest/v1/neo/3739699?api_key=t0TVs3DtDT2H8Oy2Zy8m2eVrNsAVKAexjcZXUckd"
      },
      "neo_reference_id" : "3739699",
      "name" : "(2016 AN131)",
      "nasa_jpl_url" : "http://ssd.jpl.nasa.gov/sbdb.cgi?sstr=3739699",
      "absolute_magnitude_h" : 24.1,
      "estimated_diameter" : {
        "kilometers" : {
          "estimated_diameter_min" : 0.040230458,
          "estimated_diameter_max" : 0.0899580388
        },
        "meters" : {
          "estimated_diameter_min" : 40.2304579834,
          "estimated_diameter_max" : 89.9580388169
        },
        "miles" : {
          "estimated_diameter_min" : 0.0249980399,
          "estimated_diameter_max" : 0.0558973165
        },
        "feet" : {
          "estimated_diameter_min" : 131.9896957704,
          "estimated_diameter_max" : 295.1379320721
        }
      },
      "is_potentially_hazardous_asteroid" : false,
      "close_approach_data" : [ {
        "close_approach_date" : "2016-01-22",
        "epoch_date_close_approach" : 1453449600000,
        "relative_velocity" : {
          "kilometers_per_second" : "8.8807169814",
          "kilometers_per_hour" : "31970.581133149",
          "miles_per_hour" : "19865.2758157614"
        },
        "miss_distance" : {
          "astronomical" : "0.134439644",
          "lunar" : "52.2970237732",
          "kilometers" : "20111886",
          "miles" : "12496946"
        },
        "orbiting_body" : "Earth"
      } ],
      "orbital_data" : {
        "orbit_id" : "5",
        "orbit_determination_date" : "2017-04-06 08:29:15",
        "orbit_uncertainty" : "8",
        "minimum_orbit_intersection" : ".128262",
        "jupiter_tisserand_invariant" : "4.387",
        "epoch_osculation" : "2457399.5",
        "eccentricity" : ".3327037289018411",
        "semi_major_axis" : "1.53795354858731",
        "inclination" : "11.85795240618026",
        "ascending_node_longitude" : "279.3945996731891",
        "orbital_period" : "696.6477753935869",
        "perihelion_distance" : "1.026270668094493",
        "perihelion_argument" : "240.553911584098",
        "aphelion_distance" : "2.049636429080127",
        "perihelion_time" : "2457443.597076679483",
        "mean_anomaly" : "337.2123759447233",
        "mean_motion" : ".516760424299941",
        "equinox" : "J2000"
      }
    }, {
      "links" : {
        "self" : "https://api.nasa.gov/neo/rest/v1/neo/3740496?api_key=t0TVs3DtDT2H8Oy2Zy8m2eVrNsAVKAexjcZXUckd"
      },
      "neo_reference_id" : "3740496",
      "name" : "(2016 AG193)",
      "nasa_jpl_url" : "http://ssd.jpl.nasa.gov/sbdb.cgi?sstr=3740496",
      "absolute_magnitude_h" : 23.3,
      "estimated_diameter" : {
        "kilometers" : {
          "estimated_diameter_min" : 0.058150704,
          "estimated_diameter_max" : 0.130028927
        },
        "meters" : {
          "estimated_diameter_min" : 58.1507039646,
          "estimated_diameter_max" : 130.0289270043
        },
        "miles" : {
          "estimated_diameter_min" : 0.0361331611,
          "estimated_diameter_max" : 0.0807962044
        },
        "feet" : {
          "estimated_diameter_min" : 190.7831555951,
          "estimated_diameter_max" : 426.6041048727
        }
      },
      "is_potentially_hazardous_asteroid" : false,
      "close_approach_data" : [ {
        "close_approach_date" : "2016-01-22",
        "epoch_date_close_approach" : 1453449600000,
        "relative_velocity" : {
          "kilometers_per_second" : "15.2234238768",
          "kilometers_per_hour" : "54804.3259563191",
          "miles_per_hour" : "34053.2768699139"
        },
        "miss_distance" : {
          "astronomical" : "0.1201810858",
          "lunar" : "46.7504425049",
          "kilometers" : "17978834",
          "miles" : "11171530"
        },
        "orbiting_body" : "Earth"
      } ],
      "orbital_data" : {
        "orbit_id" : "7",
        "orbit_determination_date" : "2017-04-06 08:29:03",
        "orbit_uncertainty" : "8",
        "minimum_orbit_intersection" : ".106925",
        "jupiter_tisserand_invariant" : "4.830",
        "epoch_osculation" : "2457404.5",
        "eccentricity" : ".1975461054571382",
        "semi_major_axis" : "1.311423698002703",
        "inclination" : "28.81475060288335",
        "ascending_node_longitude" : "124.2821895546575",
        "orbital_period" : "548.5458929954597",
        "perihelion_distance" : "1.052357053858071",
        "perihelion_argument" : "320.3316774743812",
        "aphelion_distance" : "1.570490342147335",
        "perihelion_time" : "2457369.149394720034",
        "mean_anomaly" : "23.19991465307187",
        "mean_motion" : ".656280549352285",
        "equinox" : "J2000"
      }
    }, {
      "links" : {
        "self" : "https://api.nasa.gov/neo/rest/v1/neo/3740823?api_key=t0TVs3DtDT2H8Oy2Zy8m2eVrNsAVKAexjcZXUckd"
      },
      "neo_reference_id" : "3740823",
      "name" : "(2016 BL1)",
      "nasa_jpl_url" : "http://ssd.jpl.nasa.gov/sbdb.cgi?sstr=3740823",
      "absolute_magnitude_h" : 21.8,
      "estimated_diameter" : {
        "kilometers" : {
          "estimated_diameter_min" : 0.1160259082,
          "estimated_diameter_max" : 0.2594418179
        },
        "meters" : {
          "estimated_diameter_min" : 116.0259082094,
          "estimated_diameter_max" : 259.4418179074
        },
        "miles" : {
          "estimated_diameter_min" : 0.0720951346,
          "estimated_diameter_max" : 0.1612096218
        },
        "feet" : {
          "estimated_diameter_min" : 380.6624406898,
          "estimated_diameter_max" : 851.1870938635
        }
      },
      "is_potentially_hazardous_asteroid" : false,
      "close_approach_data" : [ {
        "close_approach_date" : "2016-01-22",
        "epoch_date_close_approach" : 1453449600000,
        "relative_velocity" : {
          "kilometers_per_second" : "3.8443837606",
          "kilometers_per_hour" : "13839.7815380325",
          "miles_per_hour" : "8599.5020340069"
        },
        "miss_distance" : {
          "astronomical" : "0.276983776",
          "lunar" : "107.7466888428",
          "kilometers" : "41436184",
          "miles" : "25747250"
        },
        "orbiting_body" : "Earth"
      } ],
      "orbital_data" : {
        "orbit_id" : "15",
        "orbit_determination_date" : "2017-04-06 08:28:57",
        "orbit_uncertainty" : "5",
        "minimum_orbit_intersection" : ".257034",
        "jupiter_tisserand_invariant" : "4.057",
        "epoch_osculation" : "2458000.5",
        "eccentricity" : ".2975276237020335",
        "semi_major_axis" : "1.760847084241487",
        "inclination" : "7.290506538541998",
        "ascending_node_longitude" : "123.5171966949774",
        "orbital_period" : "853.4555180176723",
        "perihelion_distance" : "1.236946435564463",
        "perihelion_argument" : "344.4270581077288",
        "aphelion_distance" : "2.284747732918511",
        "perihelion_time" : "2458241.542817157500",
        "mean_anomaly" : "258.3246199189691",
        "mean_motion" : ".421814602401511",
        "equinox" : "J2000"
      }
    }, {
      "links" : {
        "self" : "https://api.nasa.gov/neo/rest/v1/neo/3740927?api_key=t0TVs3DtDT2H8Oy2Zy8m2eVrNsAVKAexjcZXUckd"
      },
      "neo_reference_id" : "3740927",
      "name" : "(2016 BY14)",
      "nasa_jpl_url" : "http://ssd.jpl.nasa.gov/sbdb.cgi?sstr=3740927",
      "absolute_magnitude_h" : 23.9,
      "estimated_diameter" : {
        "kilometers" : {
          "estimated_diameter_min" : 0.04411182,
          "estimated_diameter_max" : 0.0986370281
        },
        "meters" : {
          "estimated_diameter_min" : 44.1118199997,
          "estimated_diameter_max" : 98.6370281305
        },
        "miles" : {
          "estimated_diameter_min" : 0.0274098057,
          "estimated_diameter_max" : 0.0612901888
        },
        "feet" : {
          "estimated_diameter_min" : 144.7238235278,
          "estimated_diameter_max" : 323.6123073718
        }
      },
      "is_potentially_hazardous_asteroid" : false,
      "close_approach_data" : [ {
        "close_approach_date" : "2016-01-22",
        "epoch_date_close_approach" : 1453449600000,
        "relative_velocity" : {
          "kilometers_per_second" : "32.5248458185",
          "kilometers_per_hour" : "117089.4449466857",
          "miles_per_hour" : "72754.8276114559"
        },
        "miss_distance" : {
          "astronomical" : "0.043496948",
          "lunar" : "16.9203128815",
          "kilometers" : "6507051",
          "miles" : "4043294"
        },
        "orbiting_body" : "Earth"
      } ],
      "orbital_data" : {
        "orbit_id" : "5",
        "orbit_determination_date" : "2017-04-06 08:28:53",
        "orbit_uncertainty" : "8",
        "minimum_orbit_intersection" : ".00067436",
        "jupiter_tisserand_invariant" : "2.499",
        "epoch_osculation" : "2457417.5",
        "eccentricity" : ".9073564913198157",
        "semi_major_axis" : "2.730623677344906",
        "inclination" : "13.15878184783525",
        "ascending_node_longitude" : "123.4245413922633",
        "orbital_period" : "1648.129012284463",
        "perihelion_distance" : ".2529745583544196",
        "perihelion_argument" : "235.6378833978119",
        "aphelion_distance" : "5.208272796335391",
        "perihelion_time" : "2457370.942521376488",
        "mean_anomaly" : "10.16952688748098",
        "mean_motion" : ".2184295023731219",
        "equinox" : "J2000"
      }
    }, {
      "links" : {
        "self" : "https://api.nasa.gov/neo/rest/v1/neo/2001685?api_key=t0TVs3DtDT2H8Oy2Zy8m2eVrNsAVKAexjcZXUckd"
      },
      "neo_reference_id" : "2001685",
      "name" : "1685 Toro (1948 OA)",
      "nasa_jpl_url" : "http://ssd.jpl.nasa.gov/sbdb.cgi?sstr=2001685",
      "absolute_magnitude_h" : 14.23,
      "estimated_diameter" : {
        "kilometers" : {
          "estimated_diameter_min" : 3.7892649838,
          "estimated_diameter_max" : 8.4730540885
        },
        "meters" : {
          "estimated_diameter_min" : 3789.2649837946,
          "estimated_diameter_max" : 8473.0540885244
        },
        "miles" : {
          "estimated_diameter_min" : 2.3545393722,
          "estimated_diameter_max" : 5.264910092
        },
        "feet" : {
          "estimated_diameter_min" : 12431.9721294327,
          "estimated_diameter_max" : 27798.7347757944
        }
      },
      "is_potentially_hazardous_asteroid" : false,
      "close_approach_data" : [ {
        "close_approach_date" : "2016-01-22",
        "epoch_date_close_approach" : 1453449600000,
        "relative_velocity" : {
          "kilometers_per_second" : "16.889891887",
          "kilometers_per_hour" : "60803.6107931856",
          "miles_per_hour" : "37780.9991620214"
        },
        "miss_distance" : {
          "astronomical" : "0.1565500259",
          "lunar" : "60.8979568481",
          "kilometers" : "23419550",
          "miles" : "14552234"
        },
        "orbiting_body" : "Earth"
      } ],
      "orbital_data" : {
        "orbit_id" : "358",
        "orbit_determination_date" : "2017-04-17 06:18:55",
        "orbit_uncertainty" : "0",
        "minimum_orbit_intersection" : ".050567",
        "jupiter_tisserand_invariant" : "4.716",
        "epoch_osculation" : "2454471.5",
        "eccentricity" : ".4358741675708488",
        "semi_major_axis" : "1.367129511106032",
        "inclination" : "9.381528518103723",
        "ascending_node_longitude" : "274.3419953773255",
        "orbital_period" : "583.8656345882112",
        "perihelion_distance" : ".7712330734911489",
        "perihelion_argument" : "127.0727873528917",
        "aphelion_distance" : "1.963025948720916",
        "perihelion_time" : "2454441.625753468657",
        "mean_anomaly" : "18.41986942572597",
        "mean_motion" : ".616580217559646",
        "equinox" : "J2000"
      }
    }, {
      "links" : {
        "self" : "https://api.nasa.gov/neo/rest/v1/neo/2002062?api_key=t0TVs3DtDT2H8Oy2Zy8m2eVrNsAVKAexjcZXUckd"
      },
      "neo_reference_id" : "2002062",
      "name" : "2062 Aten (1976 AA)",
      "nasa_jpl_url" : "http://ssd.jpl.nasa.gov/sbdb.cgi?sstr=2002062",
      "absolute_magnitude_h" : 16.8,
      "estimated_diameter" : {
        "kilometers" : {
          "estimated_diameter_min" : 1.1602590821,
          "estimated_diameter_max" : 2.5944181791
        },
        "meters" : {
          "estimated_diameter_min" : 1160.2590820944,
          "estimated_diameter_max" : 2594.4181790745
        },
        "miles" : {
          "estimated_diameter_min" : 0.7209513461,
          "estimated_diameter_max" : 1.6120962183
        },
        "feet" : {
          "estimated_diameter_min" : 3806.6244068985,
          "estimated_diameter_max" : 8511.8709386348
        }
      },
      "is_potentially_hazardous_asteroid" : false,
      "close_approach_data" : [ {
        "close_approach_date" : "2016-01-22",
        "epoch_date_close_approach" : 1453449600000,
        "relative_velocity" : {
          "kilometers_per_second" : "19.7513653539",
          "kilometers_per_hour" : "71104.915274216",
          "miles_per_hour" : "44181.8291602483"
        },
        "miss_distance" : {
          "astronomical" : "0.4405227585",
          "lunar" : "171.3633575439",
          "kilometers" : "65901268",
          "miles" : "40949148"
        },
        "orbiting_body" : "Earth"
      } ],
      "orbital_data" : {
        "orbit_id" : "148",
        "orbit_determination_date" : "2015-02-24 14:25:50",
        "orbit_uncertainty" : "0",
        "minimum_orbit_intersection" : ".113146",
        "jupiter_tisserand_invariant" : "6.184",
        "epoch_osculation" : "2455926.5",
        "eccentricity" : ".1827171340905242",
        "semi_major_axis" : ".9667898316324987",
        "inclination" : "18.93368681084476",
        "ascending_node_longitude" : "108.6003764318441",
        "orbital_period" : "347.2134482250642",
        "perihelion_distance" : ".790140764328748",
        "perihelion_argument" : "148.0354055966093",
        "aphelion_distance" : "1.143438898936249",
        "perihelion_time" : "2455760.350877980336",
        "mean_anomaly" : "172.267762763347",
        "mean_motion" : "1.036826199677172",
        "equinox" : "J2000"
      }
    }, {
      "links" : {
        "self" : "https://api.nasa.gov/neo/rest/v1/neo/2357022?api_key=t0TVs3DtDT2H8Oy2Zy8m2eVrNsAVKAexjcZXUckd"
      },
      "neo_reference_id" : "2357022",
      "name" : "357022 (1999 YG3)",
      "nasa_jpl_url" : "http://ssd.jpl.nasa.gov/sbdb.cgi?sstr=2357022",
      "absolute_magnitude_h" : 19.1,
      "estimated_diameter" : {
        "kilometers" : {
          "estimated_diameter_min" : 0.4023045798,
          "estimated_diameter_max" : 0.8995803882
        },
        "meters" : {
          "estimated_diameter_min" : 402.3045798343,
          "estimated_diameter_max" : 899.5803881691
        },
        "miles" : {
          "estimated_diameter_min" : 0.2499803991,
          "estimated_diameter_max" : 0.5589731654
        },
        "feet" : {
          "estimated_diameter_min" : 1319.8969577037,
          "estimated_diameter_max" : 2951.3793207207
        }
      },
      "is_potentially_hazardous_asteroid" : true,
      "close_approach_data" : [ {
        "close_approach_date" : "2016-01-22",
        "epoch_date_close_approach" : 1453449600000,
        "relative_velocity" : {
          "kilometers_per_second" : "18.2130123232",
          "kilometers_per_hour" : "65566.8443634642",
          "miles_per_hour" : "40740.6872657314"
        },
        "miss_distance" : {
          "astronomical" : "0.2247187566",
          "lunar" : "87.4155960083",
          "kilometers" : "33617448",
          "miles" : "20888912"
        },
        "orbiting_body" : "Earth"
      } ],
      "orbital_data" : {
        "orbit_id" : "71",
        "orbit_determination_date" : "2017-04-06 09:22:57",
        "orbit_uncertainty" : "0",
        "minimum_orbit_intersection" : ".0430734",
        "jupiter_tisserand_invariant" : "4.823",
        "epoch_osculation" : "2458000.5",
        "eccentricity" : ".3295621524774158",
        "semi_major_axis" : "1.284789949497999",
        "inclination" : "34.51688657567774",
        "ascending_node_longitude" : "293.2855315685359",
        "orbital_period" : "531.9203709006454",
        "perihelion_distance" : ".8613718082600882",
        "perihelion_argument" : "250.2315182001751",
        "aphelion_distance" : "1.70820809073591",
        "perihelion_time" : "2458002.370484893225",
        "mean_anomaly" : "358.7340688599297",
        "mean_motion" : ".6767930308637164",
        "equinox" : "J2000"
      }
    }, {
      "links" : {
        "self" : "https://api.nasa.gov/neo/rest/v1/neo/3555769?api_key=t0TVs3DtDT2H8Oy2Zy8m2eVrNsAVKAexjcZXUckd"
      },
      "neo_reference_id" : "3555769",
      "name" : "(2011 BG24)",
      "nasa_jpl_url" : "http://ssd.jpl.nasa.gov/sbdb.cgi?sstr=3555769",
      "absolute_magnitude_h" : 26.6,
      "estimated_diameter" : {
        "kilometers" : {
          "estimated_diameter_min" : 0.0127219879,
          "estimated_diameter_max" : 0.0284472297
        },
        "meters" : {
          "estimated_diameter_min" : 12.7219878539,
          "estimated_diameter_max" : 28.4472296503
        },
        "miles" : {
          "estimated_diameter_min" : 0.0079050743,
          "estimated_diameter_max" : 0.0176762835
        },
        "feet" : {
          "estimated_diameter_min" : 41.7388066307,
          "estimated_diameter_max" : 93.330808926
        }
      },
      "is_potentially_hazardous_asteroid" : false,
      "close_approach_data" : [ {
        "close_approach_date" : "2016-01-22",
        "epoch_date_close_approach" : 1453449600000,
        "relative_velocity" : {
          "kilometers_per_second" : "8.1987836687",
          "kilometers_per_hour" : "29515.6212073986",
          "miles_per_hour" : "18339.8591885639"
        },
        "miss_distance" : {
          "astronomical" : "0.0740092989",
          "lunar" : "28.7896175385",
          "kilometers" : "11071634",
          "miles" : "6879594"
        },
        "orbiting_body" : "Earth"
      } ],
      "orbital_data" : {
        "orbit_id" : "6",
        "orbit_determination_date" : "2017-04-06 08:54:48",
        "orbit_uncertainty" : "7",
        "minimum_orbit_intersection" : ".0042684",
        "jupiter_tisserand_invariant" : "4.694",
        "epoch_osculation" : "2458000.5",
        "eccentricity" : ".3192067811458667",
        "semi_major_axis" : "1.402233016418051",
        "inclination" : "1.509509343562284",
        "ascending_node_longitude" : "305.52298147312",
        "orbital_period" : "606.4970737408619",
        "perihelion_distance" : ".9546307288307859",
        "perihelion_argument" : "218.5803947463555",
        "aphelion_distance" : "1.849835304005317",
        "perihelion_time" : "2458049.316532537528",
        "mean_anomaly" : "331.0238474769315",
        "mean_motion" : ".5935725258813321",
        "equinox" : "J2000"
      }
    }, {
      "links" : {
        "self" : "https://api.nasa.gov/neo/rest/v1/neo/3741971?api_key=t0TVs3DtDT2H8Oy2Zy8m2eVrNsAVKAexjcZXUckd"
      },
      "neo_reference_id" : "3741971",
      "name" : "(2016 CA30)",
      "nasa_jpl_url" : "http://ssd.jpl.nasa.gov/sbdb.cgi?sstr=3741971",
      "absolute_magnitude_h" : 27.5,
      "estimated_diameter" : {
        "kilometers" : {
          "estimated_diameter_min" : 0.008405334,
          "estimated_diameter_max" : 0.0187948982
        },
        "meters" : {
          "estimated_diameter_min" : 8.4053340207,
          "estimated_diameter_max" : 18.7948982439
        },
        "miles" : {
          "estimated_diameter_min" : 0.0052228308,
          "estimated_diameter_max" : 0.0116786047
        },
        "feet" : {
          "estimated_diameter_min" : 27.5765560686,
          "estimated_diameter_max" : 61.6630539546
        }
      },
      "is_potentially_hazardous_asteroid" : false,
      "close_approach_data" : [ {
        "close_approach_date" : "2016-01-22",
        "epoch_date_close_approach" : 1453449600000,
        "relative_velocity" : {
          "kilometers_per_second" : "6.5258101082",
          "kilometers_per_hour" : "23492.9163896732",
          "miles_per_hour" : "14597.5846311278"
        },
        "miss_distance" : {
          "astronomical" : "0.0173122077",
          "lunar" : "6.7344489098",
          "kilometers" : "2589869.5",
          "miles" : "1609270.25"
        },
        "orbiting_body" : "Earth"
      } ],
      "orbital_data" : {
        "orbit_id" : "5",
        "orbit_determination_date" : "2017-04-06 08:28:41",
        "orbit_uncertainty" : "7",
        "minimum_orbit_intersection" : ".0177474",
        "jupiter_tisserand_invariant" : "5.315",
        "epoch_osculation" : "2458000.5",
        "eccentricity" : ".2519976123887144",
        "semi_major_axis" : "1.184510104198228",
        "inclination" : "3.43502785693691",
        "ascending_node_longitude" : "137.9349308719847",
        "orbital_period" : "470.8760281200485",
        "perihelion_distance" : ".8860163860899668",
        "perihelion_argument" : "282.4758918779345",
        "aphelion_distance" : "1.483003822306488",
        "perihelion_time" : "2457830.845062727803",
        "mean_anomaly" : "129.7067036133334",
        "mean_motion" : ".7645324427265576",
        "equinox" : "J2000"
      }
    }, {
      "links" : {
        "self" : "https://api.nasa.gov/neo/rest/v1/neo/3736202?api_key=t0TVs3DtDT2H8Oy2Zy8m2eVrNsAVKAexjcZXUckd"
      },
      "neo_reference_id" : "3736202",
      "name" : "(2015 XL128)",
      "nasa_jpl_url" : "http://ssd.jpl.nasa.gov/sbdb.cgi?sstr=3736202",
      "absolute_magnitude_h" : 17.9,
      "estimated_diameter" : {
        "kilometers" : {
          "estimated_diameter_min" : 0.6991252322,
          "estimated_diameter_max" : 1.5632915441
        },
        "meters" : {
          "estimated_diameter_min" : 699.1252322458,
          "estimated_diameter_max" : 1563.2915440869
        },
        "miles" : {
          "estimated_diameter_min" : 0.4344161447,
          "estimated_diameter_max" : 0.97138403
        },
        "feet" : {
          "estimated_diameter_min" : 2293.7180269613,
          "estimated_diameter_max" : 5128.9094295021
        }
      },
      "is_potentially_hazardous_asteroid" : false,
      "close_approach_data" : [ {
        "close_approach_date" : "2016-01-22",
        "epoch_date_close_approach" : 1453449600000,
        "relative_velocity" : {
          "kilometers_per_second" : "27.6603280934",
          "kilometers_per_hour" : "99577.1811360697",
          "miles_per_hour" : "61873.3879120207"
        },
        "miss_distance" : {
          "astronomical" : "0.476098056",
          "lunar" : "185.2021484375",
          "kilometers" : "71223256",
          "miles" : "44256080"
        },
        "orbiting_body" : "Earth"
      } ],
      "orbital_data" : {
        "orbit_id" : "33",
        "orbit_determination_date" : "2017-04-06 08:30:10",
        "orbit_uncertainty" : "3",
        "minimum_orbit_intersection" : ".17965",
        "jupiter_tisserand_invariant" : "2.972",
        "epoch_osculation" : "2458000.5",
        "eccentricity" : ".6986507618107393",
        "semi_major_axis" : "2.58676370425424",
        "inclination" : "17.82162291134676",
        "ascending_node_longitude" : "42.34385094015663",
        "orbital_period" : "1519.614975365751",
        "perihelion_distance" : ".7795192716526455",
        "perihelion_argument" : "161.043035888587",
        "aphelion_distance" : "4.394008136855835",
        "perihelion_time" : "2457447.756762780094",
        "mean_anomaly" : "130.946041349239",
        "mean_motion" : ".2369021139143176",
        "equinox" : "J2000"
      }
    }, {
      "links" : {
        "self" : "https://api.nasa.gov/neo/rest/v1/neo/3766296?api_key=t0TVs3DtDT2H8Oy2Zy8m2eVrNsAVKAexjcZXUckd"
      },
      "neo_reference_id" : "3766296",
      "name" : "(2017 AH3)",
      "nasa_jpl_url" : "http://ssd.jpl.nasa.gov/sbdb.cgi?sstr=3766296",
      "absolute_magnitude_h" : 23.3,
      "estimated_diameter" : {
        "kilometers" : {
          "estimated_diameter_min" : 0.058150704,
          "estimated_diameter_max" : 0.130028927
        },
        "meters" : {
          "estimated_diameter_min" : 58.1507039646,
          "estimated_diameter_max" : 130.0289270043
        },
        "miles" : {
          "estimated_diameter_min" : 0.0361331611,
          "estimated_diameter_max" : 0.0807962044
        },
        "feet" : {
          "estimated_diameter_min" : 190.7831555951,
          "estimated_diameter_max" : 426.6041048727
        }
      },
      "is_potentially_hazardous_asteroid" : false,
      "close_approach_data" : [ {
        "close_approach_date" : "2016-01-22",
        "epoch_date_close_approach" : 1453449600000,
        "relative_velocity" : {
          "kilometers_per_second" : "9.7739867656",
          "kilometers_per_hour" : "35186.3523561056",
          "miles_per_hour" : "21863.4309959369"
        },
        "miss_distance" : {
          "astronomical" : "0.1613294282",
          "lunar" : "62.7571487427",
          "kilometers" : "24134540",
          "miles" : "14996508"
        },
        "orbiting_body" : "Earth"
      } ],
      "orbital_data" : {
        "orbit_id" : "6",
        "orbit_determination_date" : "2017-04-06 08:21:13",
        "orbit_uncertainty" : "5",
        "minimum_orbit_intersection" : ".112009",
        "jupiter_tisserand_invariant" : "5.933",
        "epoch_osculation" : "2458000.5",
        "eccentricity" : ".1188514173923319",
        "semi_major_axis" : "1.021178140895863",
        "inclination" : "17.768841172677",
        "ascending_node_longitude" : "290.7226143440226",
        "orbital_period" : "376.921309787559",
        "perihelion_distance" : ".8998096714403232",
        "perihelion_argument" : "343.6338443692473",
        "aphelion_distance" : "1.142546610351403",
        "perihelion_time" : "2457936.423629003821",
        "mean_anomaly" : "61.19975963053361",
        "mean_motion" : ".9551065186600985",
        "equinox" : "J2000"
      }
    }, {
      "links" : {
        "self" : "https://api.nasa.gov/neo/rest/v1/neo/3703540?api_key=t0TVs3DtDT2H8Oy2Zy8m2eVrNsAVKAexjcZXUckd"
      },
      "neo_reference_id" : "3703540",
      "name" : "(2015 AC44)",
      "nasa_jpl_url" : "http://ssd.jpl.nasa.gov/sbdb.cgi?sstr=3703540",
      "absolute_magnitude_h" : 24.4,
      "estimated_diameter" : {
        "kilometers" : {
          "estimated_diameter_min" : 0.0350392641,
          "estimated_diameter_max" : 0.0783501764
        },
        "meters" : {
          "estimated_diameter_min" : 35.0392641108,
          "estimated_diameter_max" : 78.3501764334
        },
        "miles" : {
          "estimated_diameter_min" : 0.0217723826,
          "estimated_diameter_max" : 0.0486845275
        },
        "feet" : {
          "estimated_diameter_min" : 114.9582192654,
          "estimated_diameter_max" : 257.0543928497
        }
      },
      "is_potentially_hazardous_asteroid" : false,
      "close_approach_data" : [ {
        "close_approach_date" : "2016-01-22",
        "epoch_date_close_approach" : 1453449600000,
        "relative_velocity" : {
          "kilometers_per_second" : "10.9924157894",
          "kilometers_per_hour" : "39572.6968417759",
          "miles_per_hour" : "24588.934879269"
        },
        "miss_distance" : {
          "astronomical" : "0.2001476127",
          "lunar" : "77.857421875",
          "kilometers" : "29941658",
          "miles" : "18604884"
        },
        "orbiting_body" : "Earth"
      } ],
      "orbital_data" : {
        "orbit_id" : "6",
        "orbit_determination_date" : "2017-08-17 06:19:02",
        "orbit_uncertainty" : "6",
        "minimum_orbit_intersection" : ".14999",
        "jupiter_tisserand_invariant" : "6.084",
        "epoch_osculation" : "2458000.5",
        "eccentricity" : ".1863309941239156",
        "semi_major_axis" : ".984982891589975",
        "inclination" : "20.4064442034547",
        "ascending_node_longitude" : "295.7782973384399",
        "orbital_period" : "357.0602113075257",
        "perihelion_distance" : ".8014500502049661",
        "perihelion_argument" : "26.55668552959023",
        "aphelion_distance" : "1.168515732974984",
        "perihelion_time" : "2457968.389550317704",
        "mean_anomaly" : "32.37482508424976",
        "mean_motion" : "1.008233313596351",
        "equinox" : "J2000"
      }
    } ]
  }
}